{
  "Gibb's Hundred Brewing Co.": {
    "brewery_link": "https://www.beeradvocate.com/beer/profile/37551/",
    "address": " - 117 W Lewis St, Greensboro",
    "rating": 0
  },
  "Wise Man Brewing": {
    "brewery_link": "https://www.beeradvocate.com/beer/profile/47200/",
    "address": " - 826 Angelo Brothers Ave, Winston-Salem",
    "rating": 0
  },
  "Brown Truck Brewery": {
    "brewery_link": "https://www.beeradvocate.com/beer/profile/44399/",
    "address": " - 1234 N Main St, High Point",
    "rating": 0
  },
  "Joymongers Brewing Co": {
    "brewery_link": "https://www.beeradvocate.com/beer/profile/46116/",
    "address": " - 508 Battleground Ave, Greensboro",
    "rating": 0
  },
  "Preyer Brewing Company": {
    "brewery_link": "https://www.beeradvocate.com/beer/profile/40341/",
    "address": " - 600 Battleground Ave, Greensboro",
    "rating": 0
  },
  "Foothills Brewing Company - Downtown Brewpub": {
    "brewery_link": "https://www.beeradvocate.com/beer/profile/11036/",
    "address": " - 638 W 4th St, Winston-Salem",
    "rating": 0
  },
  "Hoots Roller Bar & Beer Co.": {
    "brewery_link": "https://www.beeradvocate.com/beer/profile/32403/",
    "address": " - 918 Bridge St, Winston-Salem",
    "rating": 0
  },
  "Natty Greene's Pub & Brewing Co.": {
    "brewery_link": "https://www.beeradvocate.com/beer/profile/9792/",
    "address": " - 345 S. Elm Street, Greensboro",
    "rating": 0
  },
  "Pig Pounder Brewery": {
    "brewery_link": "https://www.beeradvocate.com/beer/profile/33815/",
    "address": " - 1107 Grecade St, Greensboro",
    "rating": 0
  },
  "Natty Greene's Brewing Co.": {
    "brewery_link": "https://www.beeradvocate.com/beer/profile/37226/",
    "address": " - 1918 W Lee St, Greensboro",
    "rating": 0
  },
  "Liberty Steakhouse Brewery": {
    "brewery_link": "https://www.beeradvocate.com/beer/profile/4929/",
    "address": " - 914 Mall Loop Road, High Point",
    "rating": 0
  },
  "Small Batch Beer Co.": {
    "brewery_link": "https://www.beeradvocate.com/beer/profile/32402/",
    "address": " - 241 W 5th St, Winston-Salem",
    "rating": 0
  }
}